http_injector/__init__.py
http_injector/_adapter/__init__.py
http_injector/_adapter/_Requests.py
http_injector/_context/__init__.py
http_injector/_context/CIPHERS.py
http_injector/_context/SSLContext.py
http_injector/_Httpx.py
http_injector/_Injector.py
http_injector/_Requests.py
http_injector/_utils/__init__.py
http_injector/_utils/_certificate/__init__.py
http_injector/_utils/_certificate/cacert.pem
http_injector-1.0.5.dist-info/WHEEL
http_injector-1.0.5.dist-info/METADATA
http_injector-1.0.5.dist-info/RECORD
