Metadata-Version: 2.1
Name: http-injector
Version: 1.0.5
Summary: 
Author: DesKaOne
Author-email: DesKaOne@users.noreply.github.com
Requires-Python: >=3.8,<4.0
Classifier: Programming Language :: Python :: 3
Classifier: Programming Language :: Python :: 3.8
Classifier: Programming Language :: Python :: 3.9
Classifier: Programming Language :: Python :: 3.10
Classifier: Programming Language :: Python :: 3.11
Requires-Dist: chardet (>=5.2.0,<6.0.0)
Requires-Dist: httpx[http2,socks] (>=0.27.0,<0.28.0)
Requires-Dist: requests (>=2.31.0,<3.0.0)
